aitestcraft/__init__.py
aitestcraft/ai_generator.py
aitestcraft/conf_representation.py
aitestcraft/main.py
aitestcraft/validators.py
ai_test_craft-0.1.0.dist-info/LICENSE
ai_test_craft-0.1.0.dist-info/METADATA
ai_test_craft-0.1.0.dist-info/WHEEL
ai_test_craft-0.1.0.dist-info/entry_points.txt
ai_test_craft-0.1.0.dist-info/top_level.txt
ai_test_craft-0.1.0.dist-info/RECORD
