Metadata-Version: 2.1
Name: ai-test-craft
Version: 0.1.0
Author-email: Miorey <clem.balea@gmail.com>
Project-URL: Homepage, https://github.com/Miorey/ai-test-craft
Project-URL: Issues, https://github.com/Miorey/ai-test-craft/issues
License-File: LICENSE
Requires-Dist: openai ~=1.1.0
Requires-Dist: click ~=8.1.0
Requires-Dist: halo ~=0.0.0
